{
  "slug": "5-cool-activities-that-you-must-not-miss-in-your-phuket-vacation",
  "blog_title": "5 Cool Activities That You Must Not Miss In Your Phuket Vacation",
  "seo_title": "5 Cool Activities That You Must Not Miss In Your Phuket Vacation",
  "description": "Discover the ultimate travel packing list for every adventure. Pack smart, light, and stress-free with essential tips .",
  "publish_date": "Tue Jun 17 2025",
  "images": [
    {
      "alt": "bg5-1",
      "url": "/images/logo.png"
    },
    {
      "alt": "bg5-1",
      "url": "/images/mob-logo.png"
    },
    {
      "alt": "Blog image 1",
      "url": "https://travelxploria.com/uploads_media/blog/1750183052132-thailand-1451382_1920.jpg"
    },
    {
      "alt": "Blog image 1",
      "url": "https://travelxploria.com/uploads_media/blog/1750183055824-AdobeStock_248816276.jpeg"
    },
    {
      "alt": "Blog image 2",
      "url": "https://travelxploria.com/uploads_media/blog/1750183055827-AdobeStock_296214098.jpeg"
    }
  ],
  "related_blogs": [],
  "body_content": "Published by <!-- -->travelxploria<!-- --> on <!-- -->Tue Jun 17 2025</p><div class=\"mt-8 space-y-8\"><div class=\"grid gap-4 grid-cols-1\"><div class=\"relative w-full aspect-square rounded-lg overflow-hidden shadow-md\"><img alt=\"Blog image 1\" loading=\"lazy\" class=\"rounded-lg\" style=\"position:absolute;height:100%;width:100%;left:0;top:0;right:0;bottom:0;object-fit:cover;color:transparent\" src=\"https://travelxploria.com/uploads_media/blog/1750183052132-thailand-1451382_1920.jpg\"/></div></div><div class=\"rich-content text-gray-800\"><p>It’s great if you have decided to visit Phuket this time! Located in the Andaman Sea of Southern Thailand, it’s an extremely famous tourist destination frequented by millions worldwide.<br><br>While live shows, beautiful sunsets, open sea boat tours, etc. are just like the starters, the main course has a lot more to offer! If you and your partner have been zeroing in on Phuket for a long, get hold of a travel agency, browse through different couple tour packages for Phuket, and choose the one that fits the bill.<br><br>There are plenty of cool activities to indulge in in Phuket, that can truly make your vacation an exciting one. Check out the list given below:<br><br>​<strong>It’s time to participate in some water sports:<br></strong><br>If you are a water baby and love thrills and adventures then you must know that Phuket is a water sports lover’s paradise. You can take part in various water activities in Phuket. Phuket’s west coast has top-notch facilities for water sports like windsurfing and snorkeling. Some beaches of Phuket like Layan and Nai Yang are known for kite surfing. Seasonal sports like Hobie Cat sailing and surfing are amazing as well.<br><br>​<strong>When the beautiful wild animals call you…</strong><br><br>Into wildlife? Then you would absolutely be in love with the wild safari tours offered in Khao Sok National Park and Khao Lak Park. These parks are home to a broad variety of flora and fauna. The sight of gazelles, big cats, and wild elephants will be no less than a visual treat. In addition to these, you can also go for elephant trekking, bamboo rafting, and trekking to a waterfall. The highlight will be seeing the snake charmers playing, caressing, and kissing the most dangerous snakes as part of the snake shows that are held in Phuket.​<br></p></div><div class=\"grid gap-4 grid-cols-3\"><div class=\"relative w-full aspect-square rounded-lg overflow-hidden shadow-md\"><img alt=\"Blog image 1\" loading=\"lazy\" class=\"rounded-lg\" style=\"position:absolute;height:100%;width:100%;left:0;top:0;right:0;bottom:0;object-fit:cover;color:transparent\" src=\"https://travelxploria.com/uploads_media/blog/1750183055824-AdobeStock_248816276.jpeg\"/></div><div class=\"relative w-full aspect-square rounded-lg overflow-hidden shadow-md\"><img alt=\"Blog image 2\" loading=\"lazy\" class=\"rounded-lg\" style=\"position:absolute;height:100%;width:100%;left:0;top:0;right:0;bottom:0;object-fit:cover;color:transparent\" src=\"https://travelxploria.com/uploads_media/blog/1750183055827-AdobeStock_296214098.jpeg\"/></div><div class=\"relative w-full aspect-square rounded-lg overflow-hidden shadow-md\"><img alt=\"Blog image 3\" loading=\"lazy\" class=\"rounded-lg\" style=\"position:absolute;height:100%;width:100%;left:0;top:0;right:0;bottom:0;object-fit:cover;color:transparent\" src=\"https://travelxploria.com/uploads_media/blog/1750183055839-AdobeStock_704026535.jpeg\"/></div><div class=\"relative w-full aspect-square rounded-lg overflow-hidden shadow-md\"><img alt=\"Blog image 4\" loading=\"lazy\" class=\"rounded-lg\" style=\"position:absolute;height:100%;width:100%;left:0;top:0;right:0;bottom:0;object-fit:cover;color:transparent\" src=\"https://travelxploria.com/uploads_media/blog/1750183055845-beautiful-girl-sitting-rock-james-bond-island-phang-nga-thailand.jpg\"/></div><div class=\"relative w-full aspect-square rounded-lg overflow-hidden shadow-md\"><img alt=\"Blog image 5\" loading=\"lazy\" class=\"rounded-lg\" style=\"position:absolute;height:100%;width:100%;left:0;top:0;right:0;bottom:0;object-fit:cover;color:transparent\" src=\"https://travelxploria.com/uploads_media/blog/1750183055943-thailand-2419443_1920.jpg\"/></div></div><div class=\"rich-content text-gray-800\"><p><strong>Off to island hopping:<br></strong><br>Phuket is not only the Phi-Phi islands and Similan but there are more to it. There are plenty of striking and pristine islands near Phuket which are equally beautiful. If you want to leave the crowd behind and want to do something really exciting at an exotic location then island hopping is what you should try once. The Andaman Sea around Phuket is full of stunningly beautiful tropical islands and you are bound to get mesmerized.<br><br><strong>Phuket’s 3D Trickeye Museum is so impressive:</strong><br><br>Southern Island’s first 3D Trickeye Museum is an interactive museum that is basically designed to stimulate your creativity and imagination. It engages people with the art in a new way by actually letting them become a part of it. With different 3D art to see, you will be shocked and surprised just like a 3-year-old. The quality of the paintings there is truly something. You might be asked to take off your shoes before entering the museum.<br><br><strong>Going to the topsy-turvy house:<br></strong><br>Last but not least, have you ever seen an upside-down house? Yes, the story that you heard from your grandma in childhood about a topsy-turvy town is actually true. It’s just that, in reality, it’s not a town but a house! Also known as Baan Teelanka, it’s a fun and interesting place for not only children but adults as well on any day.<br><br>So if you are humming any tune taking you to Phuket seamlessly, then get in touch with a top-rated travel agency in Kolkata for much-needed assistance in Phuket tour plan from Kolkata.<br><br></p></div></div></div><aside class=\"w-full md:w-1/3\"><div class=\"sticky top-10 p-4 border border-gray-200 rounded-xl shadow-md bg-white max-h-[90vh] overflow-y-auto no-scrollbar\"><h2 class=\"text-2xl font-semibold mb-4\">"
}